{
  "generated_at": "2025-12-06T12:26:26.895186",
  "total_countries": 250,
  "countries": {
    "AD": {
      "동물": 16,
      "식물": 227,
      "곤충": 45,
      "해양생물": 26
    },
    "AE": {
      "동물": 29,
      "식물": 5,
      "곤충": 4,
      "해양생물": 249
    },
    "AF": {
      "동물": 146,
      "식물": 121,
      "곤충": 23,
      "해양생물": 27
    },
    "AG": {
      "동물": 8,
      "식물": 10,
      "곤충": 0,
      "해양생물": 236
    },
    "AI": {
      "동물": 5,
      "식물": 0,
      "곤충": 0,
      "해양생물": 244
    },
    "AL": {
      "동물": 11,
      "식물": 178,
      "곤충": 3,
      "해양생물": 123
    },
    "AM": {
      "동물": 137,
      "식물": 129,
      "곤충": 27,
      "해양생물": 16
    },
    "AO": {
      "동물": 20,
      "식물": 56,
      "곤충": 29,
      "해양생물": 161
    },
    "BE": {
      "동물": 14,
      "식물": 184,
      "곤충": 16,
      "해양생물": 94
    },
    "BF": {
      "동물": 111,
      "식물": 99,
      "곤충": 39,
      "해양생물": 59
    },
    "BG": {
      "동물": 12,
      "식물": 191,
      "곤충": 5,
      "해양생물": 87
    },
    "BH": {
      "동물": 37,
      "식물": 5,
      "곤충": 3,
      "해양생물": 247
    },
    "BI": {
      "동물": 72,
      "식물": 98,
      "곤충": 33,
      "해양생물": 110
    },
    "BJ": {
      "동물": 39,
      "식물": 49,
      "곤충": 41,
      "해양생물": 150
    },
    "DE": {
      "동물": 11,
      "식물": 213,
      "곤충": 9,
      "해양생물": 84
    },
    "DJ": {
      "동물": 37,
      "식물": 15,
      "곤충": 19,
      "해양생물": 246
    },
    "DK": {
      "동물": 13,
      "식물": 160,
      "곤충": 13,
      "해양생물": 89
    },
    "DM": {
      "동물": 8,
      "식물": 11,
      "곤충": 3,
      "해양생물": 263
    },
    "DO": {
      "동물": 19,
      "식물": 24,
      "곤충": 4,
      "해양생물": 268
    },
    "DT": {
      "동물": 0,
      "식물": 0,
      "곤충": 1,
      "해양생물": 318
    },
    "DZ": {
      "동물": 14,
      "식물": 132,
      "곤충": 17,
      "해양생물": 118
    },
    "GL": {
      "동물": 123,
      "식물": 60,
      "곤충": 0,
      "해양생물": 98
    },
    "GM": {
      "동물": 31,
      "식물": 27,
      "곤충": 41,
      "해양생물": 215
    },
    "GN": {
      "동물": 17,
      "식물": 50,
      "곤충": 67,
      "해양생물": 178
    },
    "GP": {
      "동물": 16,
      "식물": 13,
      "곤충": 4,
      "해양생물": 257
    },
    "GQ": {
      "동물": 19,
      "식물": 54,
      "곤충": 65,
      "해양생물": 175
    },
    "GR": {
      "동물": 15,
      "식물": 163,
      "곤충": 5,
      "해양생물": 137
    },
    "GS": {
      "동물": 131,
      "식물": 21,
      "곤충": 1,
      "해양생물": 141
    },
    "GT": {
      "동물": 53,
      "식물": 27,
      "곤충": 10,
      "해양생물": 165
    },
    "GU": {
      "동물": 14,
      "식물": 9,
      "곤충": 1,
      "해양생물": 295
    },
    "GW": {
      "동물": 26,
      "식물": 32,
      "곤충": 38,
      "해양생물": 210
    },
    "GY": {
      "동물": 26,
      "식물": 36,
      "곤충": 17,
      "해양생물": 240
    },
    "HK": {
      "동물": 32,
      "식물": 43,
      "곤충": 28,
      "해양생물": 215
    },
    "HM": {
      "동물": 60,
      "식물": 2,
      "곤충": 0,
      "해양생물": 123
    },
    "HN": {
      "동물": 62,
      "식물": 26,
      "곤충": 5,
      "해양생물": 227
    },
    "HR": {
      "동물": 12,
      "식물": 161,
      "곤충": 6,
      "해양생물": 139
    },
    "HT": {
      "동물": 21,
      "식물": 24,
      "곤충": 5,
      "해양생물": 267
    },
    "HU": {
      "동물": 20,
      "식물": 221,
      "곤충": 18,
      "해양생물": 51
    },
    "ID": {
      "동물": 43,
      "식물": 22,
      "곤충": 8,
      "해양생물": 247
    },
    "IE": {
      "동물": 7,
      "식물": 139,
      "곤충": 3,
      "해양생물": 156
    },
    "IL": {
      "동물": 24,
      "식물": 67,
      "곤충": 3,
      "해양생물": 220
    },
    "IM": {
      "동물": 8,
      "식물": 110,
      "곤충": 63,
      "해양생물": 73
    },
    "IN": {
      "동물": 84,
      "식물": 38,
      "곤충": 5,
      "해양생물": 193
    },
    "IO": {
      "동물": 5,
      "식물": 6,
      "곤충": 0,
      "해양생물": 304
    },
    "IQ": {
      "동물": 55,
      "식물": 61,
      "곤충": 15,
      "해양생물": 173
    },
    "IR": {
      "동물": 79,
      "식물": 69,
      "곤충": 19,
      "해양생물": 152
    },
    "IS": {
      "동물": 7,
      "식물": 125,
      "곤충": 1,
      "해양생물": 160
    },
    "IT": {
      "동물": 15,
      "식물": 118,
      "곤충": 8,
      "해양생물": 176
    },
    "JE": {
      "동물": 8,
      "식물": 94,
      "곤충": 47,
      "해양생물": 147
    },
    "JM": {
      "동물": 11,
      "식물": 93,
      "곤충": 1,
      "해양생물": 214
    },
    "JO": {
      "동물": 51,
      "식물": 74,
      "곤충": 16,
      "해양생물": 173
    },
    "JP": {
      "동물": 4,
      "식물": 35,
      "곤충": 4,
      "해양생물": 277
    },
    "KE": {
      "동물": 17,
      "식물": 132,
      "곤충": 20,
      "해양생물": 141
    },
    "KG": {
      "동물": 164,
      "식물": 93,
      "곤충": 23,
      "해양생물": 21
    },
    "KH": {
      "동물": 27,
      "식물": 48,
      "곤충": 13,
      "해양생물": 232
    },
    "KI": {
      "동물": 9,
      "식물": 8,
      "곤충": 0,
      "해양생물": 301
    },
    "KM": {
      "동물": 11,
      "식물": 16,
      "곤충": 7,
      "해양생물": 275
    },
    "KN": {
      "동물": 12,
      "식물": 6,
      "곤충": 0,
      "해양생물": 283
    },
    "KY": {
      "동물": 12,
      "식물": 25,
      "곤충": 5,
      "해양생물": 272
    },
    "KZ": {
      "동물": 125,
      "식물": 115,
      "곤충": 33,
      "해양생물": 44
    },
    "LA": {
      "동물": 38,
      "식물": 78,
      "곤충": 36,
      "해양생물": 168
    },
    "LB": {
      "동물": 32,
      "식물": 101,
      "곤충": 8,
      "해양생물": 167
    },
    "LC": {
      "동물": 13,
      "식물": 17,
      "곤충": 3,
      "해양생물": 281
    },
    "LI": {
      "동물": 22,
      "식물": 209,
      "곤충": 41,
      "해양생물": 36
    },
    "LK": {
      "동물": 27,
      "식물": 77,
      "곤충": 12,
      "해양생물": 204
    },
    "LR": {
      "동물": 25,
      "식물": 49,
      "곤충": 66,
      "해양생물": 175
    },
    "LS": {
      "동물": 143,
      "식물": 77,
      "곤충": 79,
      "해양생물": 9
    },
    "LT": {
      "동물": 24,
      "식물": 180,
      "곤충": 31,
      "해양생물": 69
    },
    "LU": {
      "동물": 18,
      "식물": 196,
      "곤충": 36,
      "해양생물": 50
    },
    "LV": {
      "동물": 22,
      "식물": 173,
      "곤충": 33,
      "해양생물": 68
    },
    "LY": {
      "동물": 30,
      "식물": 76,
      "곤충": 16,
      "해양생물": 174
    },
    "MA": {
      "동물": 15,
      "식물": 156,
      "곤충": 23,
      "해양생물": 124
    },
    "MC": {
      "동물": 14,
      "식물": 19,
      "곤충": 5,
      "해양생물": 217
    },
    "MD": {
      "동물": 29,
      "식물": 185,
      "곤충": 71,
      "해양생물": 19
    },
    "ME": {
      "동물": 16,
      "식물": 182,
      "곤충": 6,
      "해양생물": 111
    },
    "MF": {
      "동물": 12,
      "식물": 10,
      "곤충": 0,
      "해양생물": 295
    },
    "MG": {
      "동물": 7,
      "식물": 105,
      "곤충": 4,
      "해양생물": 204
    },
    "MH": {
      "동물": 6,
      "식물": 8,
      "곤충": 0,
      "해양생물": 305
    },
    "MK": {
      "동물": 31,
      "식물": 198,
      "곤충": 15,
      "해양생물": 65
    },
    "ML": {
      "동물": 95,
      "식물": 87,
      "곤충": 52,
      "해양생물": 61
    },
    "MM": {
      "동물": 51,
      "식물": 52,
      "곤충": 3,
      "해양생물": 214
    },
    "MN": {
      "동물": 182,
      "식물": 77,
      "곤충": 19,
      "해양생물": 30
    },
    "MO": {
      "동물": 29,
      "식물": 14,
      "곤충": 6,
      "해양생물": 260
    },
    "MP": {
      "동물": 11,
      "식물": 13,
      "곤충": 0,
      "해양생물": 294
    },
    "MQ": {
      "동물": 14,
      "식물": 17,
      "곤충": 6,
      "해양생물": 282
    },
    "MR": {
      "동물": 39,
      "식물": 24,
      "곤충": 17,
      "해양생물": 230
    },
    "MS": {
      "동물": 9,
      "식물": 15,
      "곤충": 2,
      "해양생물": 288
    },
    "MT": {
      "동물": 9,
      "식물": 133,
      "곤충": 0,
      "해양생물": 160
    },
    "MU": {
      "동물": 7,
      "식물": 44,
      "곤충": 4,
      "해양생물": 262
    },
    "MV": {
      "동물": 9,
      "식물": 15,
      "곤충": 0,
      "해양생물": 295
    },
    "MW": {
      "동물": 76,
      "식물": 89,
      "곤충": 112,
      "해양생물": 39
    },
    "MX": {
      "동물": 9,
      "식물": 47,
      "곤충": 12,
      "해양생물": 252
    },
    "MY": {
      "동물": 47,
      "식물": 23,
      "곤충": 4,
      "해양생물": 243
    },
    "MZ": {
      "동물": 18,
      "식물": 77,
      "곤충": 17,
      "해양생물": 208
    },
    "NA": {
      "동물": 23,
      "식물": 92,
      "곤충": 63,
      "해양생물": 139
    },
    "NC": {
      "동물": 6,
      "식물": 20,
      "곤충": 2,
      "해양생물": 292
    },
    "NE": {
      "동물": 102,
      "식물": 87,
      "곤충": 33,
      "해양생물": 83
    },
    "NF": {
      "동물": 28,
      "식물": 14,
      "곤충": 5,
      "해양생물": 264
    },
    "NG": {
      "동물": 23,
      "식물": 76,
      "곤충": 47,
      "해양생물": 174
    },
    "NI": {
      "동물": 49,
      "식물": 17,
      "곤충": 6,
      "해양생물": 248
    },
    "NL": {
      "동물": 16,
      "식물": 181,
      "곤충": 14,
      "해양생물": 100
    },
    "NO": {
      "동물": 15,
      "식물": 180,
      "곤충": 10,
      "해양생물": 97
    },
    "NP": {
      "동물": 68,
      "식물": 145,
      "곤충": 40,
      "해양생물": 66
    },
    "NR": {
      "동물": 5,
      "식물": 4,
      "곤충": 2,
      "해양생물": 303
    },
    "NU": {
      "동물": 20,
      "식물": 10,
      "곤충": 1,
      "해양생물": 285
    },
    "NZ": {
      "동물": 21,
      "식물": 48,
      "곤충": 1,
      "해양생물": 227
    },
    "OM": {
      "동물": 36,
      "식물": 25,
      "곤충": 9,
      "해양생물": 246
    },
    "PA": {
      "동물": 76,
      "식물": 21,
      "곤충": 15,
      "해양생물": 208
    },
    "PE": {
      "동물": 36,
      "식물": 72,
      "곤충": 43,
      "해양생물": 169
    },
    "PF": {
      "동물": 2,
      "식물": 15,
      "곤충": 0,
      "해양생물": 302
    },
    "PG": {
      "동물": 20,
      "식물": 15,
      "곤충": 3,
      "해양생물": 282
    },
    "PH": {
      "동물": 7,
      "식물": 19,
      "곤충": 3,
      "해양생물": 291
    },
    "PK": {
      "동물": 76,
      "식물": 87,
      "곤충": 18,
      "해양생물": 136
    },
    "PL": {
      "동물": 16,
      "식물": 210,
      "곤충": 20,
      "해양생물": 71
    },
    "PM": {
      "동물": 137,
      "식물": 33,
      "곤충": 0,
      "해양생물": 126
    },
    "PN": {
      "동물": 32,
      "식물": 17,
      "곤충": 1,
      "해양생물": 262
    },
    "PR": {
      "동물": 10,
      "식물": 22,
      "곤충": 2,
      "해양생물": 286
    },
    "PS": {
      "동물": 61,
      "식물": 114,
      "곤충": 62,
      "해양생물": 66
    },
    "PT": {
      "동물": 7,
      "식물": 186,
      "곤충": 2,
      "해양생물": 121
    },
    "PW": {
      "동물": 7,
      "식물": 10,
      "곤충": 0,
      "해양생물": 303
    },
    "PY": {
      "동물": 126,
      "식물": 79,
      "곤충": 54,
      "해양생물": 61
    },
    "QA": {
      "동물": 31,
      "식물": 13,
      "곤충": 6,
      "해양생물": 242
    },
    "RE": {
      "동물": 14,
      "식물": 14,
      "곤충": 4,
      "해양생물": 286
    },
    "RO": {
      "동물": 12,
      "식물": 213,
      "곤충": 8,
      "해양생물": 81
    },
    "RS": {
      "동물": 27,
      "식물": 240,
      "곤충": 9,
      "해양생물": 38
    },
    "RU": {
      "동물": 29,
      "식물": 180,
      "곤충": 12,
      "해양생물": 97
    },
    "RW": {
      "동물": 97,
      "식물": 152,
      "곤충": 45,
      "해양생물": 22
    },
    "SA": {
      "동물": 50,
      "식물": 40,
      "곤충": 9,
      "해양생물": 216
    },
    "SB": {
      "동물": 14,
      "식물": 18,
      "곤충": 1,
      "해양생물": 287
    },
    "SC": {
      "동물": 3,
      "식물": 14,
      "곤충": 73,
      "해양생물": 224
    },
    "SD": {
      "동물": 36,
      "식물": 55,
      "곤충": 13,
      "해양생물": 215
    },
    "SE": {
      "동물": 20,
      "식물": 193,
      "곤충": 11,
      "해양생물": 78
    },
    "SG": {
      "동물": 29,
      "식물": 65,
      "곤충": 16,
      "해양생물": 209
    },
    "SH": {
      "동물": 8,
      "식물": 30,
      "곤충": 62,
      "해양생물": 200
    },
    "SI": {
      "동물": 11,
      "식물": 199,
      "곤충": 5,
      "해양생물": 101
    },
    "SJ": {
      "동물": 89,
      "식물": 171,
      "곤충": 3,
      "해양생물": 31
    },
    "SK": {
      "동물": 26,
      "식물": 202,
      "곤충": 16,
      "해양생물": 54
    },
    "SL": {
      "동물": 35,
      "식물": 61,
      "곤충": 71,
      "해양생물": 151
    },
    "SM": {
      "동물": 51,
      "식물": 110,
      "곤충": 56,
      "해양생물": 24
    },
    "SN": {
      "동물": 26,
      "식물": 53,
      "곤충": 39,
      "해양생물": 199
    },
    "SO": {
      "동물": 19,
      "식물": 60,
      "곤충": 10,
      "해양생물": 230
    },
    "SR": {
      "동물": 29,
      "식물": 25,
      "곤충": 17,
      "해양생물": 246
    },
    "SS": {
      "동물": 115,
      "식물": 88,
      "곤충": 70,
      "해양생물": 40
    },
    "ST": {
      "동물": 12,
      "식물": 34,
      "곤충": 8,
      "해양생물": 249
    },
    "SV": {
      "동물": 68,
      "식물": 32,
      "곤충": 20,
      "해양생물": 198
    },
    "SX": {
      "동물": 10,
      "식물": 10,
      "곤충": 0,
      "해양생물": 298
    },
    "SY": {
      "동물": 47,
      "식물": 83,
      "곤충": 12,
      "해양생물": 161
    },
    "SZ": {
      "동물": 99,
      "식물": 128,
      "곤충": 46,
      "해양생물": 36
    },
    "TC": {
      "동물": 6,
      "식물": 14,
      "곤충": 0,
      "해양생물": 297
    },
    "TD": {
      "동물": 97,
      "식물": 71,
      "곤충": 48,
      "해양생물": 80
    },
    "TF": {
      "동물": 15,
      "식물": 3,
      "곤충": 0,
      "해양생물": 300
    },
    "TG": {
      "동물": 48,
      "식물": 47,
      "곤충": 56,
      "해양생물": 166
    },
    "TH": {
      "동물": 47,
      "식물": 35,
      "곤충": 2,
      "해양생물": 236
    },
    "TJ": {
      "동물": 168,
      "식물": 105,
      "곤충": 24,
      "해양생물": 18
    },
    "TK": {
      "동물": 14,
      "식물": 3,
      "곤충": 1,
      "해양생물": 295
    },
    "TL": {
      "동물": 21,
      "식물": 19,
      "곤충": 3,
      "해양생물": 277
    },
    "TM": {
      "동물": 177,
      "식물": 73,
      "곤충": 22,
      "해양생물": 44
    },
    "TN": {
      "동물": 22,
      "식물": 100,
      "곤충": 34,
      "해양생물": 153
    },
    "TO": {
      "동물": 5,
      "식물": 11,
      "곤충": 0,
      "해양생물": 303
    },
    "TR": {
      "동물": 28,
      "식물": 194,
      "곤충": 7,
      "해양생물": 88
    },
    "TT": {
      "동물": 16,
      "식물": 13,
      "곤충": 7,
      "해양생물": 279
    },
    "TV": {
      "동물": 5,
      "식물": 5,
      "곤충": 0,
      "해양생물": 305
    },
    "TW": {
      "동물": 12,
      "식물": 22,
      "곤충": 4,
      "해양생물": 282
    },
    "TZ": {
      "동물": 13,
      "식물": 262,
      "곤충": 19,
      "해양생물": 26
    },
    "UA": {
      "동물": 11,
      "식물": 231,
      "곤충": 10,
      "해양생물": 66
    },
    "UG": {
      "동물": 22,
      "식물": 83,
      "곤충": 157,
      "해양생물": 51
    },
    "UM": {
      "동물": 2,
      "식물": 7,
      "곤충": 0,
      "해양생물": 303
    },
    "US": {
      "동물": 3,
      "식물": 33,
      "곤충": 4,
      "해양생물": 280
    },
    "UY": {
      "동물": 50,
      "식물": 40,
      "곤충": 22,
      "해양생물": 201
    },
    "UZ": {
      "동물": 175,
      "식물": 90,
      "곤충": 25,
      "해양생물": 24
    },
    "VA": {
      "동물": 27,
      "식물": 78,
      "곤충": 36,
      "해양생물": 20
    },
    "VC": {
      "동물": 13,
      "식물": 9,
      "곤충": 2,
      "해양생물": 291
    },
    "VE": {
      "동물": 27,
      "식물": 25,
      "곤충": 42,
      "해양생물": 224
    },
    "VG": {
      "동물": 11,
      "식물": 5,
      "곤충": 0,
      "해양생물": 300
    },
    "VI": {
      "동물": 17,
      "식물": 13,
      "곤충": 0,
      "해양생물": 290
    },
    "VN": {
      "동물": 42,
      "식물": 46,
      "곤충": 3,
      "해양생물": 229
    },
    "VU": {
      "동물": 7,
      "식물": 15,
      "곤충": 1,
      "해양생물": 295
    },
    "WF": {
      "동물": 6,
      "식물": 5,
      "곤충": 1,
      "해양생물": 304
    },
    "WS": {
      "동물": 13,
      "식물": 9,
      "곤충": 0,
      "해양생물": 294
    },
    "YE": {
      "동물": 39,
      "식물": 66,
      "곤충": 4,
      "해양생물": 211
    },
    "YT": {
      "동물": 9,
      "식물": 18,
      "곤충": 9,
      "해양생물": 282
    },
    "ZA": {
      "동물": 15,
      "식물": 45,
      "곤충": 27,
      "해양생물": 227
    },
    "ZM": {
      "동물": 20,
      "식물": 64,
      "곤충": 110,
      "해양생물": 121
    },
    "ZW": {
      "동물": 82,
      "식물": 95,
      "곤충": 85,
      "해양생물": 57
    }
  }
}